casual_mcp_server_time/__init__.py
casual_mcp_server_time/cli.py
casual_mcp_server_time/server.py
casual_mcp_server_time-1.0.0.dist-info/METADATA
casual_mcp_server_time-1.0.0.dist-info/WHEEL
casual_mcp_server_time-1.0.0.dist-info/entry_points.txt
casual_mcp_server_time-1.0.0.dist-info/top_level.txt
casual_mcp_server_time-1.0.0.dist-info/RECORD
