Metadata-Version: 2.4
Name: casual-mcp-server-time
Version: 1.0.0
Summary: Time and date utilities as a FastMCP server
Author: Alex Stansfield
License: MIT
Project-URL: Homepage, https://github.com/casualgenius/mcp-servers
Project-URL: Issues, https://github.com/casualgenius/mcp-servers/issues
Project-URL: Source, https://github.com/casualgenius/mcp-servers
Requires-Python: >=3.11
Requires-Dist: fastmcp
Requires-Dist: pydantic
Requires-Dist: dateparser
